README.md
setup.py
Byrd.egg-info/PKG-INFO
Byrd.egg-info/SOURCES.txt
Byrd.egg-info/dependency_links.txt
Byrd.egg-info/entry_points.txt
Byrd.egg-info/requires.txt
Byrd.egg-info/top_level.txt
byrd/__init__.py
byrd/cli.py
byrd/config.py
byrd/main.py
byrd/utils.py
byrd/pkg/az.yaml
byrd/pkg/git.yaml
byrd/pkg/misc.yaml
byrd/pkg/os.yaml
byrd/pkg/pg.yaml
byrd/pkg/py.yaml