Metadata-Version: 1.0
Name: Byrd
Version: 0.0.3
Summary: Simple deployment tool based on Paramiko
Home-page: https://bitbucket.org/bertrandchenal/byrd
Author: Bertrand Chenal
Author-email: bertrand@adimian.com
License: MIT
Platform: UNKNOWN
